Metadata-Version: 2.0
Name: emr-launcher-aws
Version: 1.0.0
Summary: AWS plugin providing template functions for emr_launcher
Home-page: https://github.com/tuneinc/emr_launcher_aws
Author: Nick Rushton
Author-email: nick@tune.com
License: MIT
Platform: UNKNOWN
Classifier: License :: OSI Approved :: MIT License
Classifier: Programming Language :: Python
Classifier: Programming Language :: Python :: 2.7
Classifier: Programming Language :: Python :: 3
Classifier: Programming Language :: Python :: 3.6
Classifier: Programming Language :: Python :: Implementation :: CPython
Classifier: Programming Language :: Python :: Implementation :: PyPy
Requires-Python: >=2.7.0
Requires-Dist: boto3 (==1.4.4)
